prokabaddidata/__init__.py
prokabaddidata/main.py
prokabaddidata/original_code.py
prokabaddidata/prokabaddidata.py
pro_kabaddi_data-0.1.2.dist-info/LICENSE
pro_kabaddi_data-0.1.2.dist-info/METADATA
pro_kabaddi_data-0.1.2.dist-info/WHEEL
pro_kabaddi_data-0.1.2.dist-info/top_level.txt
pro_kabaddi_data-0.1.2.dist-info/RECORD
