Metadata-Version: 2.1
Name: pro_kabaddi_data
Version: 0.1.2
Summary: A Python module for aggregating Kabaddi data
Author-email: Bhaskar Lalwani <bhaskarlalwani2040@gmail.com>, Aniruddha Mukherjee <mukh.aniruddha@example.com>
License: MIT License
Project-URL: Homepage, https://github.com/annimukherjee/ProKabaddi_API
Project-URL: Bug Tracker, https://github.com/annimukherjee/ProKabaddi_API/issues
Project-URL: Docs, https://annimukherjee.github.io/ProKabaddi_API/
Keywords: kabaddi,data,aggregator
Classifier: Development Status :: 3 - Alpha
Classifier: Intended Audience :: Developers
Classifier: License :: OSI Approved :: MIT License
Classifier: Operating System :: OS Independent
Classifier: Programming Language :: Python :: 3
Classifier: Programming Language :: Python :: 3.7
Classifier: Programming Language :: Python :: 3.8
Classifier: Programming Language :: Python :: 3.9
Classifier: Programming Language :: Python :: 3.10
Requires-Python: >=3.7
License-File: LICENSE
Requires-Dist: selenium
Requires-Dist: pandas
Requires-Dist: beautifulsoup4
